{
    "4KfC923EFsY": "Guy Yelling Among Us Sound Effect",
    "8-pOCeuXhDM": "Danger Alarm Meme Sound Effect",
    "C7aGuETBzw8": "AMOGUS Sound effect",
    "Ns3YxbIhTRM": "Official Among Us In Real Life Official Music Video - Rebecca Zamolo Shorts",
    "TApmI8YtYhc": "Dramatic Vine_Instagram Boom - Sound Effect (HD)",
    "ZKuDJQqy6ak": "among us trap remix loud (full)",
    "grd-K33tOSM": "Among Us Trap Remix (Among Drip Theme Song Original)",
    "oq4yO5G8eAM": "IMPOSTER-DAMIAN (beat by Be-Twiin)"
}
